CSVrope-1.0.0.dist-info/DESCRIPTION.rst
CSVrope-1.0.0.dist-info/METADATA
CSVrope-1.0.0.dist-info/RECORD
CSVrope-1.0.0.dist-info/WHEEL
CSVrope-1.0.0.dist-info/metadata.json
CSVrope-1.0.0.dist-info/top_level.txt
csvrope/__init__.py
csvrope/csvrope.py
