Metadata-Version: 2.0
Name: CSVrope
Version: 1.0.0
Summary: A set of row-operations for CSV files.
Home-page: https://github.com/thumbo/CSVrope
Author: thumbo
Author-email: UNKNOWN
License: Creative Commons Attribution 4.0 International license
Keywords: csv edit utility row operation
Platform: UNKNOWN
Requires-Dist: nose
